huaweicloudsdkiotda/__init__.py
huaweicloudsdkiotda/v5/__init__.py
huaweicloudsdkiotda/v5/iotda_async_client.py
huaweicloudsdkiotda/v5/iotda_client.py
huaweicloudsdkiotda/v5/auth/__init__.py
huaweicloudsdkiotda/v5/auth/iotda_credentials.py
huaweicloudsdkiotda/v5/model/__init__.py
huaweicloudsdkiotda/v5/model/action_device_alarm.py
huaweicloudsdkiotda/v5/model/action_device_command.py
huaweicloudsdkiotda/v5/model/action_smn_forwarding.py
huaweicloudsdkiotda/v5/model/add_action_req.py
huaweicloudsdkiotda/v5/model/add_application.py
huaweicloudsdkiotda/v5/model/add_application_request.py
huaweicloudsdkiotda/v5/model/add_application_response.py
huaweicloudsdkiotda/v5/model/add_backlog_policy.py
huaweicloudsdkiotda/v5/model/add_bridge.py
huaweicloudsdkiotda/v5/model/add_bridge_request.py
huaweicloudsdkiotda/v5/model/add_bridge_response.py
huaweicloudsdkiotda/v5/model/add_certificate_request.py
huaweicloudsdkiotda/v5/model/add_certificate_response.py
huaweicloudsdkiotda/v5/model/add_device.py
huaweicloudsdkiotda/v5/model/add_device_group_dto.py
huaweicloudsdkiotda/v5/model/add_device_group_request.py
huaweicloudsdkiotda/v5/model/add_device_group_response.py
huaweicloudsdkiotda/v5/model/add_device_proxy.py
huaweicloudsdkiotda/v5/model/add_device_request.py
huaweicloudsdkiotda/v5/model/add_device_response.py
huaweicloudsdkiotda/v5/model/add_export_task.py
huaweicloudsdkiotda/v5/model/add_flow_control_policy.py
huaweicloudsdkiotda/v5/model/add_functions_request.py
huaweicloudsdkiotda/v5/model/add_functions_response.py
huaweicloudsdkiotda/v5/model/add_harmony_soft_bus_dto.py
huaweicloudsdkiotda/v5/model/add_harmony_soft_bus_request.py
huaweicloudsdkiotda/v5/model/add_harmony_soft_bus_response.py
huaweicloudsdkiotda/v5/model/add_product.py
huaweicloudsdkiotda/v5/model/add_queue_request.py
huaweicloudsdkiotda/v5/model/add_queue_response.py
huaweicloudsdkiotda/v5/model/add_rule_req.py
huaweicloudsdkiotda/v5/model/add_security_profile_dto.py
huaweicloudsdkiotda-3.1.184.dist-info/METADATA
huaweicloudsdkiotda-3.1.184.dist-info/WHEEL
huaweicloudsdkiotda-3.1.184.dist-info/licenses/LICENSE
huaweicloudsdkiotda-3.1.184.dist-info/RECORD
